pkr/__init__.py
pkr/__main__.py
pkr/environment.py
pkr/kard.py
pkr/utils.py
pkr/version.py
pkr/cli/__init__.py
pkr/cli/action.py
pkr/cli/log.py
pkr/cli/parser.py
pkr/driver/__init__.py
pkr/driver/base.py
pkr/driver/buildx.py
pkr/driver/buildx_compose.py
pkr/driver/buildx_k8s.py
pkr/driver/docker.py
pkr/driver/docker_compose.py
pkr/driver/k8s.py
pkr/ext/__init__.py
pkr/ext/auto_volume.py
pkr/ext/basic_template.py
pkr-2.0.1.dist-info/licenses/LICENSE
pkr-2.0.1.dist-info/licenses/NOTICE
pkr-2.0.1.dist-info/METADATA
pkr-2.0.1.dist-info/WHEEL
pkr-2.0.1.dist-info/entry_points.txt
pkr-2.0.1.dist-info/top_level.txt
pkr-2.0.1.dist-info/RECORD
